MANIFEST.in
README.md
setup.cfg
setup.py
mocked_tests/__init__.py
mocked_tests/tests/__init__.py
mocked_tests/tests/test_1.py
mocked_tests/tests/test_2.py
mocked_tests/tests/test_3.py
test_executor/__init__.py
test_executor/common.py
test_executor.egg-info/PKG-INFO
test_executor.egg-info/SOURCES.txt
test_executor.egg-info/dependency_links.txt
test_executor.egg-info/top_level.txt
test_executor/.pytest_cache/README.md
test_executor/abstract_test/__init__.py
test_executor/abstract_test/abstract_test.py
test_executor/abstract_test/test_result.py
test_executor/elastic_object/__init__.py
test_executor/elastic_object/elastic_object.py
test_executor/logger_factory/__init__.py
test_executor/logger_factory/logger_factory.py
test_executor/test_generation/__init__.py
test_executor/test_generation/test_executor.py
test_executor/test_generation/test_loader.py
test_executor/test_generation/test_runnable.py