Metadata-Version: 2.1
Name: test-executor
Version: 0.0.12
Summary: This modules allows you to execute tests in the best way possible!
Home-page: https://github.com/idan57/test_executor
Author: Idan Cohen
Author-email: idan57@gmail.com
License: UNKNOWN
Platform: UNKNOWN
Classifier: Programming Language :: Python :: 3
Classifier: Operating System :: OS Independent
Classifier: Topic :: Software Development :: Build Tools
Requires-Python: >=3.6
